zun/MANIFEST.in
zun/__init__.py
zun/version.py
zun/api/__init__.py
zun/api/app.py
zun/api/config.py
zun/api/hooks.py
zun/api/http_error.py
zun/api/rest_api_version_history.rst
zun/api/servicegroup.py
zun/api/utils.py
zun/api/versioned_method.py
zun/api/wsgi.py
zun/api/controllers/__init__.py
zun/api/controllers/base.py
zun/api/controllers/link.py
zun/api/controllers/root.py
zun/api/controllers/versions.py
zun/api/controllers/v1/__init__.py
zun/api/controllers/v1/availability_zone.py
zun/api/controllers/v1/capsules.py
zun/api/controllers/v1/collection.py
zun/api/controllers/v1/containers.py
zun/api/controllers/v1/hosts.py
zun/api/controllers/v1/images.py
zun/api/controllers/v1/networks.py
zun/api/controllers/v1/quota_classes.py
zun/api/controllers/v1/quotas.py
zun/api/controllers/v1/registries.py
zun/api/controllers/v1/zun_services.py
zun/api/controllers/v1/schemas/__init__.py
zun/api/controllers/v1/schemas/capsules.py
zun/api/controllers/v1/schemas/containers.py
zun/api/controllers/v1/schemas/images.py
zun/api/controllers/v1/schemas/network.py
zun/api/controllers/v1/schemas/parameter_types.py
zun/api/controllers/v1/schemas/quota_classes.py
zun/api/controllers/v1/schemas/quotas.py
zun/api/controllers/v1/schemas/registries.py
zun/api/controllers/v1/schemas/services.py
zun/api/controllers/v1/views/__init__.py
zun/api/controllers/v1/views/actions_view.py
zun/api/controllers/v1/views/availability_zone_view.py
zun/api/controllers/v1/views/capsules_view.py
zun/api/controllers/v1/views/containers_view.py
zun/api/controllers/v1/views/hosts_view.py
zun/api/controllers/v1/views/images_view.py
zun/api/controllers/v1/views/network_view.py
zun/api/controllers/v1/views/registries_view.py
zun/api/controllers/v1/views/services_view.py
zun/api/middleware/__init__.py
zun/api/middleware/auth_token.py
zun/api/middleware/parsable_error.py
zun/api/validation/__init__.py
zun/api/validation/validators.py
zun/cmd/__init__.py
zun/cmd/api.py
zun/cmd/compute.py
zun/cmd/db_manage.py
zun-16.0.0.dist-info/AUTHORS
zun-16.0.0.dist-info/LICENSE
zun-16.0.0.dist-info/METADATA
zun-16.0.0.dist-info/WHEEL
zun-16.0.0.dist-info/entry_points.txt
zun-16.0.0.dist-info/pbr.json
zun-16.0.0.dist-info/top_level.txt
zun-16.0.0.dist-info/RECORD
