Metadata-Version: 2.1
Name: zun
Version: 16.0.0
Summary: OpenStack Containers service
Home-page: https://docs.openstack.org/zun/latest/
Author: OpenStack
Author-email: openstack-discuss@lists.openstack.org
Classifier: Environment :: OpenStack
Classifier: Intended Audience :: Information Technology
Classifier: Intended Audience :: System Administrators
Classifier: License :: OSI Approved :: Apache Software License
Classifier: Operating System :: POSIX :: Linux
Classifier: Programming Language :: Python
Classifier: Programming Language :: Python :: 3
Classifier: Programming Language :: Python :: 3.8
Classifier: Programming Language :: Python :: 3.9
Classifier: Programming Language :: Python :: 3.10
Classifier: Programming Language :: Python :: 3.11
License-File: LICENSE
License-File: AUTHORS
Requires-Dist: cotyledon >=1.5.0
Requires-Dist: Flask >=0.12.3
Requires-Dist: futurist >=1.6.0
Requires-Dist: grpcio >=1.25.0
Requires-Dist: PyYAML >=5.1
Requires-Dist: eventlet >=0.28.0
Requires-Dist: WebOb >=1.8.1
Requires-Dist: alembic >=0.9.8
Requires-Dist: keystoneauth1 >=3.14.0
Requires-Dist: keystonemiddleware >=9.0.0
Requires-Dist: kuryr-lib >=0.5.0
Requires-Dist: pbr >=5.5.0
Requires-Dist: pecan >=1.3.3
Requires-Dist: protobuf >=3.6.0
Requires-Dist: psutil >=3.2.2
Requires-Dist: python-glanceclient >=3.2.0
Requires-Dist: python-neutronclient >=7.2.0
Requires-Dist: python-cinderclient >=7.1.0
Requires-Dist: requests >=2.20.1
Requires-Dist: oslo.i18n >=5.0.0
Requires-Dist: oslo.log >=4.2.0
Requires-Dist: oslo.concurrency >=4.1.0
Requires-Dist: oslo.config >=8.1.0
Requires-Dist: oslo.messaging >=14.1.0
Requires-Dist: oslo.middleware >=4.1.0
Requires-Dist: oslo.policy >=4.5.0
Requires-Dist: oslo.privsep >=2.2.0
Requires-Dist: oslo.serialization >=3.2.0
Requires-Dist: oslo.service >=2.2.0
Requires-Dist: oslo.versionedobjects >=2.1.0
Requires-Dist: oslo.context >=3.1.0
Requires-Dist: oslo.utils >=4.5.0
Requires-Dist: oslo.db >=8.2.0
Requires-Dist: oslo.rootwrap >=5.8.0
Requires-Dist: oslo.upgradecheck >=1.3.0
Requires-Dist: os-brick >=3.1.0
Requires-Dist: os-resource-classes >=0.1.0
Requires-Dist: os-traits >=0.15.0
Requires-Dist: os-vif >=1.15.1
Requires-Dist: SQLAlchemy >=1.2.0
Requires-Dist: stevedore >=3.3.0
Requires-Dist: docker >=4.3.0
Requires-Dist: neutron-lib >=1.13.0
Requires-Dist: retrying >=1.3.3
Requires-Dist: tenacity >=6.0.0
Requires-Dist: websockify >=0.8.0
Requires-Dist: websocket-client >=0.44.0
Requires-Dist: pyroute2 >=0.5.7 ; (sys_platform!='win32')
Provides-Extra: osprofiler
Requires-Dist: osprofiler >=3.4.0 ; extra == 'osprofiler'
Provides-Extra: test
Requires-Dist: hacking <3.1.0,>=3.0.1 ; extra == 'test'
Requires-Dist: bandit >=1.1.0 ; extra == 'test'
Requires-Dist: doc8 >=0.8.1 ; extra == 'test'
Requires-Dist: coverage >=5.3 ; extra == 'test'
Requires-Dist: fixtures >=3.0.0 ; extra == 'test'
Requires-Dist: oslotest >=4.4.1 ; extra == 'test'
Requires-Dist: osprofiler >=3.4.0 ; extra == 'test'
Requires-Dist: PyMySQL >=0.7.6 ; extra == 'test'
Requires-Dist: tempest >=17.1.0 ; extra == 'test'
Requires-Dist: testresources >=2.0.0 ; extra == 'test'
Requires-Dist: testscenarios >=0.4 ; extra == 'test'
Requires-Dist: testtools >=2.4.0 ; extra == 'test'
Requires-Dist: stestr >=3.1.0 ; extra == 'test'
Requires-Dist: Pygments >=2.7.2 ; extra == 'test'
Requires-Dist: python-zunclient >=4.1.0 ; extra == 'test'
Requires-Dist: WebTest >=2.0.26 ; extra == 'test'
